rasahub_debug/__init__.py
rasahub_debug-0.0.2.dist-info/METADATA
rasahub_debug-0.0.2.dist-info/RECORD
rasahub_debug-0.0.2.dist-info/WHEEL
rasahub_debug-0.0.2.dist-info/top_level.txt
