Metadata-Version: 2.1
Name: rasahub-debug
Version: 0.0.2
Summary: Debugging connector for Rasahub
Home-page: http://github.com/frommie/rasahub-debug
Author: Christian Frommert
Author-email: christian.frommert@gmail.com
License: MIT
Keywords: rasahub
Platform: UNKNOWN
Classifier: Development Status :: 3 - Alpha
Classifier: Intended Audience :: Developers
Classifier: License :: OSI Approved :: MIT License
Classifier: Programming Language :: Python :: 2.7
Classifier: Topic :: Software Development
Provides-Extra: test
Requires-Dist: rasahub
Requires-Dist: rasahub-debug-client
Provides-Extra: test
